{
  "minecraft:recipes/transportation/acacia_boat": {
    "criteria": {
      "in_water": "2019-04-15 18:13:57 -0700"
    },
    "done": true
  },
  "minecraft:recipes/transportation/oak_boat": {
    "criteria": {
      "in_water": "2019-04-15 18:13:57 -0700"
    },
    "done": true
  },
  "minecraft:recipes/transportation/dark_oak_boat": {
    "criteria": {
      "in_water": "2019-04-15 18:13:57 -0700"
    },
    "done": true
  },
  "minecraft:recipes/transportation/birch_boat": {
    "criteria": {
      "in_water": "2019-04-15 18:13:57 -0700"
    },
    "done": true
  },
  "minecraft:recipes/transportation/jungle_boat": {
    "criteria": {
      "in_water": "2019-04-15 18:13:57 -0700"
    },
    "done": true
  },
  "minecraft:recipes/transportation/spruce_boat": {
    "criteria": {
      "in_water": "2019-04-15 18:13:57 -0700"
    },
    "done": true
  },
  "minecraft:adventure/adventuring_time": {
    "criteria": {
      "minecraft:forest": "2019-04-06 21:48:17 -0700"
    },
    "done": false
  }
}