{
  "minecraft:recipes/building_blocks/purple_wool": {
    "criteria": {
      "has_white_wool": "2018-07-15 00:16:39 -0700"
    },
    "done": true
  },
  "minecraft:recipes/tools/wooden_axe": {
    "criteria": {
      "has_stick": "2018-07-15 17:25:18 -0700"
    },
    "done": true
  },
  "minecraft:recipes/building_blocks/lime_wool": {
    "criteria": {
      "has_white_wool": "2018-07-15 00:16:39 -0700"
    },
    "done": true
  },
  "minecraft:recipes/redstone/lever": {
    "criteria": {
      "has_cobblestone": "2018-07-14 20:06:01 -0700"
    },
    "done": true
  },
  "minecraft:recipes/decorations/blue_bed": {
    "criteria": {
      "has_blue_wool": "2018-07-14 23:42:58 -0700"
    },
    "done": true
  },
  "minecraft:recipes/building_blocks/pillar_quartz_block": {
    "criteria": {
      "has_quartz_block": "2018-07-15 17:46:06 -0700"
    },
    "done": true
  },
  "minecraft:recipes/building_blocks/black_wool": {
    "criteria": {
      "has_white_wool": "2018-07-15 00:16:39 -0700"
    },
    "done": true
  },
  "minecraft:recipes/redstone/spruce_door": {
    "criteria": {
      "has_planks": "2018-07-14 20:14:55 -0700"
    },
    "done": true
  },
  "minecraft:recipes/decorations/white_bed": {
    "criteria": {
      "has_white_wool": "2018-07-15 00:16:39 -0700"
    },
    "done": true
  },
  "minecraft:recipes/building_blocks/green_wool": {
    "criteria": {
      "has_white_wool": "2018-07-15 00:16:39 -0700"
    },
    "done": true
  },
  "minecraft:recipes/redstone/spruce_fence_gate": {
    "criteria": {
      "has_planks": "2018-07-14 20:14:55 -0700"
    },
    "done": true
  },
  "minecraft:recipes/building_blocks/brown_wool": {
    "criteria": {
      "has_white_wool": "2018-07-15 00:16:39 -0700"
    },
    "done": true
  },
  "minecraft:recipes/decorations/magenta_bed": {
    "criteria": {
      "has_magenta_wool": "2018-07-15 01:47:23 -0700"
    },
    "done": true
  },
  "minecraft:recipes/decorations/crafting_table": {
    "criteria": {
      "has_planks": "2018-07-14 20:14:55 -0700"
    },
    "done": true
  },
  "minecraft:recipes/redstone/redstone": {
    "criteria": {
      "has_redstone_block": "2018-07-15 00:14:29 -0700"
    },
    "done": true
  },
  "minecraft:recipes/building_blocks/magenta_wool": {
    "criteria": {
      "has_white_wool": "2018-07-15 00:16:39 -0700"
    },
    "done": true
  },
  "minecraft:recipes/redstone/trapdoor": {
    "criteria": {
      "has_planks": "2018-07-14 20:14:55 -0700"
    },
    "done": true
  },
  "minecraft:recipes/misc/leather": {
    "criteria": {
      "has_rabbit_hide": "2018-07-30 21:50:15 -0700"
    },
    "done": true
  },
  "minecraft:recipes/decorations/ladder": {
    "criteria": {
      "has_stick": "2018-07-15 17:25:18 -0700"
    },
    "done": true
  },
  "minecraft:recipes/decorations/chest": {
    "criteria": {
      "has_lots_of_items": "2018-07-14 19:49:37 -0700"
    },
    "done": true
  },
  "minecraft:end/elytra": {
    "criteria": {
      "elytra": "2018-08-22 20:37:31 -0700"
    },
    "done": true
  },
  "minecraft:recipes/decorations/painting": {
    "criteria": {
      "has_wool": "2018-07-14 23:42:58 -0700"
    },
    "done": true
  },
  "minecraft:recipes/building_blocks/quartz_slab": {
    "criteria": {
      "has_quartz_block": "2018-07-15 17:46:06 -0700"
    },
    "done": true
  },
  "minecraft:recipes/decorations/pink_bed": {
    "criteria": {
      "has_pink_wool": "2018-07-15 00:00:22 -0700"
    },
    "done": true
  },
  "minecraft:recipes/decorations/pink_carpet": {
    "criteria": {
      "has_pink_wool": "2018-07-15 00:00:22 -0700"
    },
    "done": true
  },
  "minecraft:recipes/tools/wooden_shovel": {
    "criteria": {
      "has_stick": "2018-07-15 17:25:18 -0700"
    },
    "done": true
  },
  "minecraft:recipes/redstone/wooden_pressure_plate": {
    "criteria": {
      "has_planks": "2018-07-14 20:14:55 -0700"
    },
    "done": true
  },
  "minecraft:recipes/building_blocks/purpur_stairs": {
    "criteria": {
      "has_purpur_block": "2018-07-15 00:00:22 -0700"
    },
    "done": true
  },
  "minecraft:recipes/building_blocks/cyan_wool": {
    "criteria": {
      "has_white_wool": "2018-07-15 00:16:39 -0700"
    },
    "done": true
  },
  "minecraft:recipes/misc/stick": {
    "criteria": {
      "has_planks": "2018-07-14 20:14:55 -0700"
    },
    "done": true
  },
  "minecraft:recipes/building_blocks/stone_slab": {
    "criteria": {
      "has_stone": "2018-07-30 21:34:39 -0700"
    },
    "done": true
  },
  "minecraft:recipes/decorations/sign": {
    "criteria": {
      "has_planks": "2018-07-14 20:14:55 -0700"
    },
    "done": true
  },
  "minecraft:recipes/transportation/spruce_boat": {
    "criteria": {
      "entered_water": "2018-07-30 21:57:13 -0700"
    },
    "done": true
  },
  "minecraft:recipes/tools/flint_and_steel": {
    "criteria": {
      "has_obsidian": "2018-07-14 19:38:40 -0700"
    },
    "done": true
  },
  "minecraft:recipes/building_blocks/light_blue_wool": {
    "criteria": {
      "has_white_wool": "2018-07-15 00:16:39 -0700"
    },
    "done": true
  },
  "minecraft:recipes/tools/stone_shovel": {
    "criteria": {
      "has_cobblestone": "2018-07-14 20:06:01 -0700"
    },
    "done": true
  },
  "minecraft:recipes/redstone/wooden_button": {
    "criteria": {
      "has_planks": "2018-07-14 20:14:55 -0700"
    },
    "done": true
  },
  "minecraft:recipes/combat/wooden_sword": {
    "criteria": {
      "has_stick": "2018-07-15 17:25:18 -0700"
    },
    "done": true
  },
  "minecraft:recipes/decorations/blue_carpet": {
    "criteria": {
      "has_blue_wool": "2018-07-14 23:42:58 -0700"
    },
    "done": true
  },
  "minecraft:recipes/building_blocks/oak_planks": {
    "criteria": {
      "has_log": "2018-07-14 19:30:39 -0700"
    },
    "done": true
  },
  "minecraft:recipes/building_blocks/emerald_block": {
    "criteria": {
      "has_at_least_9_emerald": "2018-08-22 20:47:31 -0700"
    },
    "done": true
  },
  "minecraft:recipes/building_blocks/gray_wool": {
    "criteria": {
      "has_white_wool": "2018-07-15 00:16:39 -0700"
    },
    "done": true
  },
  "minecraft:recipes/building_blocks/sandstone_stairs": {
    "criteria": {
      "has_sandstone": "2018-07-14 19:27:35 -0700"
    },
    "done": true
  },
  "minecraft:recipes/tools/wooden_hoe": {
    "criteria": {
      "has_stick": "2018-07-15 17:25:18 -0700"
    },
    "done": true
  },
  "minecraft:recipes/building_blocks/andesite": {
    "criteria": {
      "has_stone": "2018-07-15 18:33:30 -0700"
    },
    "done": true
  },
  "minecraft:recipes/building_blocks/cobblestone_slab": {
    "criteria": {
      "has_cobblestone": "2018-07-14 20:06:01 -0700"
    },
    "done": true
  },
  "minecraft:recipes/building_blocks/chiseled_quartz_block": {
    "criteria": {
      "has_quartz_block": "2018-07-15 17:46:06 -0700"
    },
    "done": true
  },
  "minecraft:recipes/building_blocks/spruce_wooden_slab": {
    "criteria": {
      "has_planks": "2018-07-14 20:14:55 -0700"
    },
    "done": true
  },
  "minecraft:recipes/decorations/white_banner": {
    "criteria": {
      "has_white_wool": "2018-07-15 00:16:39 -0700"
    },
    "done": true
  },
  "minecraft:recipes/redstone/stone_button": {
    "criteria": {
      "has_stone": "2018-07-30 21:34:39 -0700"
    },
    "done": true
  },
  "minecraft:recipes/decorations/pink_banner": {
    "criteria": {
      "has_pink_wool": "2018-07-15 00:00:22 -0700"
    },
    "done": true
  },
  "minecraft:recipes/building_blocks/yellow_wool": {
    "criteria": {
      "has_white_wool": "2018-07-15 00:16:39 -0700"
    },
    "done": true
  },
  "minecraft:recipes/decorations/magenta_carpet": {
    "criteria": {
      "has_magenta_wool": "2018-07-15 01:47:23 -0700"
    },
    "done": true
  },
  "minecraft:story/form_obsidian": {
    "criteria": {
      "obsidian": "2018-07-14 19:38:40 -0700"
    },
    "done": true
  },
  "minecraft:recipes/building_blocks/sandstone_slab": {
    "criteria": {
      "has_sandstone": "2018-07-14 19:27:35 -0700"
    },
    "done": true
  },
  "minecraft:recipes/misc/emerald": {
    "criteria": {
      "has_emerald_block": "2018-07-16 22:04:27 -0700"
    },
    "done": true
  },
  "minecraft:recipes/building_blocks/smooth_sandstone": {
    "criteria": {
      "has_sandstone": "2018-07-14 19:27:35 -0700"
    },
    "done": true
  },
  "minecraft:recipes/building_blocks/blue_wool": {
    "criteria": {
      "has_white_wool": "2018-07-15 00:16:39 -0700"
    },
    "done": true
  },
  "minecraft:story/mine_stone": {
    "criteria": {
      "get_stone": "2018-07-14 20:06:01 -0700"
    },
    "done": true
  },
  "minecraft:recipes/decorations/furnace": {
    "criteria": {
      "has_cobblestone": "2018-07-14 20:06:01 -0700"
    },
    "done": true
  },
  "minecraft:recipes/misc/yellow_dye_from_sunflower": {
    "criteria": {
      "has_double_plant": "2018-07-30 21:36:10 -0700"
    },
    "done": true
  },
  "minecraft:recipes/brewing/cauldron": {
    "criteria": {
      "has_water_bucket": "2018-07-16 22:15:56 -0700"
    },
    "done": true
  },
  "minecraft:adventure/adventuring_time": {
    "criteria": {
      "taiga": "2018-07-14 19:25:11 -0700",
      "desert": "2018-07-14 19:25:57 -0700"
    },
    "done": false
  },
  "minecraft:recipes/decorations/armor_stand": {
    "criteria": {
      "has_stone_slab": "2018-07-30 21:14:17 -0700"
    },
    "done": true
  },
  "minecraft:recipes/building_blocks/spruce_planks": {
    "criteria": {
      "has_log": "2018-07-14 20:06:35 -0700"
    },
    "done": true
  },
  "minecraft:recipes/building_blocks/purpur_slab": {
    "criteria": {
      "has_purpur_block": "2018-07-15 00:00:22 -0700"
    },
    "done": true
  },
  "minecraft:recipes/building_blocks/orange_wool": {
    "criteria": {
      "has_white_wool": "2018-07-15 00:16:39 -0700"
    },
    "done": true
  },
  "minecraft:recipes/tools/wooden_pickaxe": {
    "criteria": {
      "has_stick": "2018-07-15 17:25:18 -0700"
    },
    "done": true
  },
  "minecraft:recipes/building_blocks/stone_brick_slab": {
    "criteria": {
      "has_stonebrick": "2018-07-14 19:30:12 -0700"
    },
    "done": true
  },
  "minecraft:recipes/transportation/birch_boat": {
    "criteria": {
      "entered_water": "2018-07-30 21:57:13 -0700"
    },
    "done": true
  },
  "minecraft:recipes/combat/stone_sword": {
    "criteria": {
      "has_cobblestone": "2018-07-14 20:06:01 -0700"
    },
    "done": true
  },
  "minecraft:recipes/building_blocks/quartz_stairs": {
    "criteria": {
      "has_quartz_block": "2018-07-15 17:46:06 -0700"
    },
    "done": true
  },
  "minecraft:recipes/decorations/cobblestone_wall": {
    "criteria": {
      "has_cobblestone": "2018-07-14 20:06:01 -0700"
    },
    "done": true
  },
  "minecraft:recipes/decorations/enchanting_table": {
    "criteria": {
      "has_obsidian": "2018-07-14 19:38:40 -0700"
    },
    "done": true
  },
  "minecraft:recipes/decorations/magenta_banner": {
    "criteria": {
      "has_magenta_wool": "2018-07-15 01:47:23 -0700"
    },
    "done": true
  },
  "minecraft:recipes/transportation/acacia_boat": {
    "criteria": {
      "entered_water": "2018-07-30 21:57:13 -0700"
    },
    "done": true
  },
  "minecraft:recipes/tools/stone_pickaxe": {
    "criteria": {
      "has_cobblestone": "2018-07-14 20:06:01 -0700"
    },
    "done": true
  },
  "minecraft:adventure/root": {
    "criteria": {
      "killed_something": "2018-07-16 22:15:49 -0700"
    },
    "done": true
  },
  "minecraft:recipes/redstone/stone_pressure_plate": {
    "criteria": {
      "has_stone": "2018-07-30 21:34:39 -0700"
    },
    "done": true
  },
  "minecraft:recipes/transportation/boat": {
    "criteria": {
      "entered_water": "2018-07-30 21:57:13 -0700"
    },
    "done": true
  },
  "minecraft:recipes/transportation/jungle_boat": {
    "criteria": {
      "entered_water": "2018-07-30 21:57:13 -0700"
    },
    "done": true
  },
  "minecraft:recipes/tools/stone_hoe": {
    "criteria": {
      "has_cobblestone": "2018-07-14 20:06:01 -0700"
    },
    "done": true
  },
  "minecraft:recipes/decorations/spruce_fence": {
    "criteria": {
      "has_planks": "2018-07-14 20:14:55 -0700"
    },
    "done": true
  },
  "minecraft:recipes/building_blocks/purpur_pillar": {
    "criteria": {
      "has_purpur_block": "2018-07-15 00:00:22 -0700"
    },
    "done": true
  },
  "minecraft:recipes/transportation/dark_oak_boat": {
    "criteria": {
      "entered_water": "2018-07-30 21:57:13 -0700"
    },
    "done": true
  },
  "minecraft:recipes/building_blocks/pink_wool": {
    "criteria": {
      "has_white_wool": "2018-07-15 00:16:39 -0700"
    },
    "done": true
  },
  "minecraft:recipes/building_blocks/stonebrick": {
    "criteria": {
      "has_stone": "2018-07-30 21:34:39 -0700"
    },
    "done": true
  },
  "minecraft:recipes/decorations/white_carpet": {
    "criteria": {
      "has_white_wool": "2018-07-15 00:16:39 -0700"
    },
    "done": true
  },
  "minecraft:recipes/building_blocks/spruce_stairs": {
    "criteria": {
      "has_planks": "2018-07-14 20:14:55 -0700"
    },
    "done": true
  },
  "minecraft:recipes/building_blocks/stone_stairs": {
    "criteria": {
      "has_cobblestone": "2018-07-14 20:06:01 -0700"
    },
    "done": true
  },
  "minecraft:recipes/building_blocks/polished_diorite": {
    "criteria": {
      "has_stone": "2018-07-15 18:33:30 -0700"
    },
    "done": true
  },
  "minecraft:recipes/building_blocks/light_gray_wool": {
    "criteria": {
      "has_white_wool": "2018-07-15 00:16:39 -0700"
    },
    "done": true
  },
  "minecraft:recipes/building_blocks/red_wool": {
    "criteria": {
      "has_white_wool": "2018-07-15 00:16:39 -0700"
    },
    "done": true
  },
  "minecraft:recipes/tools/stone_axe": {
    "criteria": {
      "has_cobblestone": "2018-07-14 20:06:01 -0700"
    },
    "done": true
  },
  "minecraft:recipes/decorations/blue_banner": {
    "criteria": {
      "has_blue_wool": "2018-07-14 23:42:58 -0700"
    },
    "done": true
  },
  "minecraft:recipes/building_blocks/chiseled_stonebrick": {
    "criteria": {
      "has_stonebrick": "2018-07-14 19:30:12 -0700"
    },
    "done": true
  },
  "minecraft:recipes/building_blocks/stone_brick_stairs": {
    "criteria": {
      "has_stonebrick": "2018-07-14 19:30:12 -0700"
    },
    "done": true
  }
}